timelapse_slicer/__init__.py
timelapse_slicer/timelapse_slicer.py
timelapse_slicer-1.0.5.dist-info/LICENSE.txt
timelapse_slicer-1.0.5.dist-info/METADATA
timelapse_slicer-1.0.5.dist-info/WHEEL
timelapse_slicer-1.0.5.dist-info/top_level.txt
timelapse_slicer-1.0.5.dist-info/RECORD
