Metadata-Version: 2.1
Name: timelapse-slicer
Version: 1.0.5
Summary: UNKNOWN
Home-page: https://github.com/petez-sufe/timelapse_slicer
Author: Xi Zhao
Author-email: xz3068@columbia.edu
License: MIT
Keywords: timelapse slicer
Platform: UNKNOWN
License-File: LICENSE.txt
Requires-Dist: pillow
Requires-Dist: tqdm
